{
  "event_id": "2433596",
  "event_title": "왕가의 산책",
  "fetched_at": "2026-06-01T06:33:54.467661",
  "reviews": [
    {
      "title": "왕가의 산책-인천 중구 2026. 01. 05 - 2026.12. 31",
      "description": "전통문화행사인 왕가의 산책은 조선시대 궁중생활을 재현하는 행사이다. 제1여객터미널에서는 왕과 왕비가 궁궐을 산책하는 모습이 재현된다. 제2여객터미널에서는 조선 후기 무과 전시장에 거둥 왕과 무관의...",
      "link": "http://cafe.naver.com/kwdkr/50547",
      "cafe_name": "그대가 있어 오늘도 웃습니다.",
      "cafe_url": "https://cafe.naver.com/kwdkr",
      "date": ""
    },
    {
      "title": "일본 오키나와현 나하 시내 마츠야마 중심 권역",
      "description": "일본 오키나와현 나하 시내 마츠야마 중심 권역 나미노우에 해변 산책과 혼자 여유롭게 머문 호텔 칵테일... 은근히 후기 평점이 훌륭하게 유지되고 있는 알짜배기 거점이기도 합니다. 거품 가득한 불필요한 대형 시설...",
      "link": "http://cafe.naver.com/hassrd/14019",
      "cafe_name": "여행가서 모하지",
      "cafe_url": "https://cafe.naver.com/hassrd",
      "date": ""
    },
    {
      "title": "그림책과 산책 5월 모임 후기",
      "description": "합스부르크 왕가의 두 자매 이야기(축약)...늘 간절히 염원하였으나 결과적으로는 전혀 다른 삶을 살게... (끝) **** 적은 이 후기 : 그림책을 함께 읽고, 느낌을 이야기하면서 공감해 보고, 또 함께 걷는 산책길이 참...",
      "link": "http://cafe.naver.com/hansalimbseoul/9346",
      "cafe_name": "한살림북서울생협",
      "cafe_url": "https://cafe.naver.com/hansalimbseoul",
      "date": ""
    },
    {
      "title": "어젯 밤 창덕궁 달빛기행 다녀왔어요",
      "description": "홈페이지 * 후기 중간 중간 생략한 부분이 있을 수 있어요 날씨가 흐리긴 했지만 선선하니 걷기 좋은 늦은... 밤산책 왕가의 산책을 만날 수 있는 부용지,부용정에 다다라요 다들 임금님과 왕비님 사이에서 사진을 찍는데...",
      "link": "http://cafe.naver.com/naganda/481255",
      "cafe_name": "나홀로 여행가기 나만의 추억만들기『...",
      "cafe_url": "https://cafe.naver.com/naganda",
      "date": ""
    },
    {
      "title": "독일 뮌헨 한달살기 - 숙소·교통·음식·옥토버페스트·알프스 당일치기 지역별 분석·비용·주의사항",
      "description": "바이에른 왕가 여름 궁전·정원 → 조용하고 안전한 고급 주거 지역 → 지하철 트람 (Tram) 으로 구시가지 약 25분 5060 님펜부르크 장점 → 님펜부르크 궁전 정원 = 매일 아침 산책 → 왕궁 운하 = 여름 보트...",
      "link": "http://cafe.naver.com/bluehillgolf/171",
      "cafe_name": "5060한달살기클럽",
      "cafe_url": "https://cafe.naver.com/bluehillgolf",
      "date": ""
    }
  ]
}