{
  "event_id": "2497537-2026-42k",
  "event_title": "2026 한강나이트워크42K",
  "fetched_at": "2026-06-07T20:11:01.843822",
  "reviews": [
    {
      "title": "2026 한강나이트워크 42K 접수방법·코스 완벽 가이드",
      "description": "2026 한강나이트워크 42K 얼리버드 접수부터 코스 안내까지! 할인 혜택과 완주 준비 꿀팁까지! 도심 야경과 강바람 속에서 즐기는 2026 한강나이트워크 42K가 다시 찾아왔습니다. 한 여름 밤의 특별한 경험, 놓치면 후회할...",
      "link": "http://cafe.naver.com/pluslifeplus/168",
      "cafe_name": "일상의 플러스",
      "cafe_url": "https://cafe.naver.com/pluslifeplus",
      "date": ""
    },
    {
      "title": "2026 한강나이트워크 42K",
      "description": "♂️2026 한강나이트워크♀️ 한여름 서울 야경을 즐기며 밤산책하는 경험 흔치않을 겁니다 달리는 마라톤이 부담되시는 분들 평소 산책을 좋아하시는 분들 가족, 친구랑 같이 여름 추억 만들고 싶으신 분들 너무...",
      "link": "http://cafe.naver.com/rfcrossfit/10820",
      "cafe_name": "리폼드 김포",
      "cafe_url": "https://cafe.naver.com/rfcrossfit",
      "date": ""
    }
  ]
}