{
  "event_id": "2826964",
  "event_title": "그루브 인 관악",
  "fetched_at": "2026-06-07T20:10:57.557900",
  "reviews": [
    {
      "title": "2026-1학기 개인실기 교수님별 수업 시간 안내(수정)",
      "description": "7 관악 교수명 개인실기 지도 방향 요일, 교시 수강인원(명) 김성준 기본적인 악기테크닉을 시작으로 주법, 호흡법, 핑거링, 스케일 등을 기본으로 하며, 곡 트랜스크립션 방법, 아티큘레이션, 그루브, 즉흥연주 등을...",
      "link": "http://cafe.naver.com/buappliedmusic/27135",
      "cafe_name": "백석대학교 문화예술학부 실용음악과",
      "cafe_url": "https://cafe.naver.com/buappliedmusic",
      "date": ""
    }
  ]
}